README
filtercoffee.py
setup.py
FilterCoffee.egg-info/PKG-INFO
FilterCoffee.egg-info/SOURCES.txt
FilterCoffee.egg-info/dependency_links.txt
FilterCoffee.egg-info/top_level.txt
filtercoffee.egg-info/SOURCES.txt