Metadata-Version: 1.0
Name: filtercoffee
Version: 0.3
Summary: A simple WSGI Middleware for compiling CoffeeScript to JavaScript on the fly
Home-page: http://github.com/clj/filtercoffee
Author: Christian Lyder Jacobsen
Author-email: christian@lyderjacobsen.net
License: BSD
Download-URL: https://github.com/downloads/clj/filtercoffee/filtercoffee-0.3.tar.gz
Platform: UNKNOWN
Classifier: Topic :: Internet :: WWW/HTTP :: WSGI :: Middleware
Classifier: License :: OSI Approved :: BSD License
Classifier: Intended Audience :: Developers
Classifier: Operating System :: OS Independent
Classifier: Development Status :: 3 - Alpha
Classifier: Programming Language :: JavaScript
Classifier: Programming Language :: Python
